{
  "project_info": {
    "project_number": "114205613647",
    "project_id": "project-101-heart-connect",
    "storage_bucket": "project-101-heart-connect.appspot.com"
  },
  "client": [
    {
      "client_info": {
        "mobilesdk_app_id": "1:114205613647:android:b824ba6a1763af568bd43a",
        "android_client_info": {
          "package_name": "com.appdevhangout.project101heartconnect"
        }
      },
      "oauth_client": [],
      "api_key": [
        {
          "current_key": "AIzaSyBIjBbQnJQ83PJqJn-hji8Xv4qeCs3Iq-M"
        }
      ],
      "services": {
        "appinvite_service": {
          "other_platform_oauth_client": []
        }
      }
    }
  ],
  "configuration_version": "1"
}